setup.py
bin/withings
withings/__init__.py
withings.egg-info/PKG-INFO
withings.egg-info/SOURCES.txt
withings.egg-info/dependency_links.txt
withings.egg-info/requires.txt
withings.egg-info/top_level.txt
withings.egg-info/zip-safe