Metadata-Version: 1.0
Name: withings
Version: 0.3
Summary: Library for the Withings API
Home-page: https://github.com/maximebf/python-withings
Author: Maxime Bouroumeau-Fuseau
Author-email: maxime.bouroumeau@gmail.com
License: MIT License
Keywords: withings
Platform: UNKNOWN
